MANIFEST.in
README.md
setup.cfg
setup.py
django_event_queue.egg-info/PKG-INFO
django_event_queue.egg-info/SOURCES.txt
django_event_queue.egg-info/dependency_links.txt
django_event_queue.egg-info/requires.txt
django_event_queue.egg-info/top_level.txt
event_queue/__init__.py
event_queue/admin.py
event_queue/apps.py
event_queue/event_process.py
event_queue/long_poll.py
event_queue/models.py
event_queue/tests.py
event_queue/utils.py
event_queue/views.py
event_queue/migrations/0001_initial.py
event_queue/migrations/0002_auto_20171123_0506.py
event_queue/migrations/0003_eventqueuemodel_task_name.py
event_queue/migrations/0004_auto_20171127_0238.py
event_queue/migrations/0005_auto_20171214_0350.py
event_queue/migrations/0006_auto_20171221_0659.py
event_queue/migrations/__init__.py