Metadata-Version: 1.0
Name: django-event-queue
Version: 0.1.20
Summary: Python Event Queue
Home-page: https://github.com/ducminhgd/event-queue
Author: Gia Duong Duc Minh
Author-email: giaduongducminh@gmail.com
License: UNKNOWN
Platform: UNKNOWN
